{"version":1,"resource":"vscode-userdata:/User/settings.json","entries":[{"id":"kYj0.json","timestamp":1765012157611},{"id":"kVeu.json","timestamp":1765012165336},{"id":"R5r7.json","timestamp":1765096903293},{"id":"AF1t.json","timestamp":1765274652162},{"id":"itv9.json","timestamp":1765441132187},{"id":"RgTa.json","timestamp":1765465948740},{"id":"0xDn.json","timestamp":1765732371598},{"id":"b74B.json","timestamp":1765798100479},{"id":"vYFz.json","timestamp":1765816814330},{"id":"mS8k.json","timestamp":1765816814454},{"id":"mihg.json","timestamp":1765816820868},{"id":"W9nX.json","timestamp":1765883249591},{"id":"gkpV.json","timestamp":1765883249665},{"id":"BM5w.json","timestamp":1765883250153},{"id":"pkUh.json","timestamp":1765883261422},{"id":"bj6k.json","timestamp":1765896580562},{"id":"sOap.json","timestamp":1765896580626},{"id":"GZ0F.json","timestamp":1765896580691},{"id":"m5y2.json","timestamp":1765896580777},{"id":"mLHm.json","timestamp":1765896586431},{"id":"tpjl.json","timestamp":1765953045564},{"id":"RiNf.json","timestamp":1766229058778},{"id":"QEra.json","timestamp":1766312557411},{"id":"v3fc.json","timestamp":1766472233240},{"id":"qX1g.json","timestamp":1766730709600},{"id":"i8sT.json","timestamp":1766769929130},{"id":"xMSG.json","timestamp":1766831740457},{"id":"2plM.json","timestamp":1766917771067},{"id":"cg3S.json","timestamp":1766990020614},{"id":"S6r9.json","timestamp":1766990020630},{"id":"mf39.json","timestamp":1766990020646},{"id":"nMpk.json","timestamp":1766990020664},{"id":"ggT3.json","timestamp":1766990020682},{"id":"2MJr.json","timestamp":1766990020711},{"id":"hKI0.json","timestamp":1766990026849},{"id":"RoNq.json","timestamp":1767116872960},{"id":"tSVU.json","timestamp":1767116873013},{"id":"eSAo.json","timestamp":1767116873064},{"id":"hg7B.json","timestamp":1767116873080},{"id":"1ZSt.json","timestamp":1767116873094},{"id":"mvts.json","timestamp":1767116873111},{"id":"8kr9.json","timestamp":1767116873144},{"id":"JqI4.json","timestamp":1767116884733},{"id":"8AM4.json","timestamp":1767594101552},{"id":"gM0X.json","timestamp":1767693650863},{"id":"XXXd.json","timestamp":1767814815664},{"id":"GVc4.json","timestamp":1767856717866}]}