{"version":1,"resource":"vscode-remote://970-cs-47df324f-2954-4137-ae6a-3c67f0e3146d.cs-europe-west1-xedi.cloudshell.dev/home/lanzamientosocupacional/backend/config/env.js","entries":[{"id":"hODQ.js","timestamp":1767861784217},{"id":"P90v.js","timestamp":1767862201848},{"id":"M2U6.js","timestamp":1767862812946},{"id":"LbBa.js","timestamp":1767863289332},{"id":"P4ag.js","timestamp":1767863426743},{"id":"XNiu.js","timestamp":1767863589910},{"id":"vDEC.js","timestamp":1767869550446},{"id":"WHbe.js","timestamp":1767869564075},{"id":"trzm.js","timestamp":1767871622497},{"id":"C1Ei.js","timestamp":1767881320903},{"id":"tZCV.js","timestamp":1767881343702},{"id":"k0kG.js","timestamp":1767881437009},{"id":"lfbh.js","timestamp":1767883190814}]}