{"version":1,"resource":"vscode-remote://970-cs-47df324f-2954-4137-ae6a-3c67f0e3146d.cs-europe-west1-xedi.cloudshell.dev/home/lanzamientosocupacional/public-next/src/app/setup/page.tsx","entries":[{"id":"WmYa.tsx","timestamp":1766845394493},{"id":"tGkF.tsx","timestamp":1766846334989},{"id":"TBAH.tsx","timestamp":1766846445587},{"id":"bu02.tsx","timestamp":1766846653395},{"id":"yPTs.tsx","timestamp":1766846890288},{"id":"tF1o.tsx","source":"Convert to named function","timestamp":1766846904017},{"id":"VmQB.tsx","timestamp":1766846951514},{"id":"HpWk.tsx","timestamp":1766847230286},{"id":"BqLj.tsx","timestamp":1766847336877},{"id":"a48d.tsx","timestamp":1766847603034},{"id":"L7Yx.tsx","timestamp":1766847918242},{"id":"lv6F.tsx","timestamp":1766848129300},{"id":"GnfC.tsx","source":"undoRedo.source","timestamp":1766848138536},{"id":"jpUT.tsx","timestamp":1766848153023},{"id":"Tulb.tsx","timestamp":1766848176526},{"id":"oPIL.tsx","timestamp":1766848215127},{"id":"Vq0b.tsx","timestamp":1766848232955},{"id":"6qsL.tsx","timestamp":1766848271046},{"id":"C6lQ.tsx","timestamp":1766848408423},{"id":"4DwY.tsx","timestamp":1766848500291},{"id":"T4rV.tsx","timestamp":1766848532549},{"id":"HSax.tsx","timestamp":1766848653023},{"id":"Xvdz.tsx","timestamp":1766858718057},{"id":"Do5a.tsx","timestamp":1766858825087},{"id":"YJmI.tsx","source":"undoRedo.source","timestamp":1766858839863},{"id":"86vE.tsx","timestamp":1766858862388},{"id":"SOcb.tsx","timestamp":1766858929070},{"id":"XWYd.tsx","timestamp":1766859657781},{"id":"Mb7z.tsx","timestamp":1766859778279},{"id":"2Mu2.tsx","timestamp":1766859862743},{"id":"pqOQ.tsx","timestamp":1766908777436},{"id":"JQ88.tsx","source":"undoRedo.source","timestamp":1766908792426},{"id":"cnGi.tsx","timestamp":1766909034286},{"id":"6HWJ.tsx","timestamp":1767785954346},{"id":"Fkom.tsx","timestamp":1767787285315},{"id":"cPxl.tsx","timestamp":1767787566654},{"id":"9cFG.tsx","timestamp":1767789365448},{"id":"9hDy.tsx","timestamp":1767796286314},{"id":"uxZl.tsx","timestamp":1767796432980},{"id":"HukC.tsx","timestamp":1767874178183},{"id":"QvI5.tsx","timestamp":1767874310127}]}